sra_quick_submit_package/__init__.py
sra_quick_submit_package/sra_quick_submit.py
sra_quick_submit-1.8.dist-info/AUTHORS.rst
sra_quick_submit-1.8.dist-info/LICENSE
sra_quick_submit-1.8.dist-info/METADATA
sra_quick_submit-1.8.dist-info/WHEEL
sra_quick_submit-1.8.dist-info/entry_points.txt
sra_quick_submit-1.8.dist-info/top_level.txt
sra_quick_submit-1.8.dist-info/RECORD
