Metadata-Version: 2.1
Name: sra-quick-submit
Version: 1.8
Summary: Pip package for SRA Quick-Submit, a goofy SRA submission tool from 2013.
Home-page: https://github.com/crashfrog/sra_quick_submit
Author: Justin Payne
Author-email: justin.payne@fda.hhs.gov
License: UNKNOWN
Keywords: sra_quick_submit_package
Platform: UNKNOWN
Classifier: Development Status :: 2 - Pre-Alpha
Classifier: Intended Audience :: Developers
Classifier: Natural Language :: English
Classifier: Programming Language :: Python :: 3
Classifier: Programming Language :: Python :: 3.5
Classifier: Programming Language :: Python :: 3.6
Classifier: Programming Language :: Python :: 3.7
Classifier: Programming Language :: Python :: 3.8
Requires-Python: >=3.5
